helloworld.py
helloworld_apoorva_vaidya-0.0.1.dist-info/METADATA
helloworld_apoorva_vaidya-0.0.1.dist-info/WHEEL
helloworld_apoorva_vaidya-0.0.1.dist-info/top_level.txt
helloworld_apoorva_vaidya-0.0.1.dist-info/RECORD
