Metadata-Version: 2.1
Name: helloworld-apoorva-vaidya
Version: 0.0.1
Summary: Say Hello!
Home-page: UNKNOWN
License: UNKNOWN
Platform: UNKNOWN
